ptan/__init__.py
ptan/actions.py
ptan/agent.py
ptan/experience.py
ptan/ignite.py
ptan/common/__init__.py
ptan/common/runfile.py
ptan/common/utils.py
ptan/common/wrappers.py
ptan/common/wrappers_simple.py
tests/__init__.py
tests/conftest.py
tests/test_actions.py
tests/test_agent.py
tests/test_experience.py
tests/common/__init__.py
tests/common/test_utils.py
tests/common/test_wrappers_simple.py
ptan-0.8.1.dist-info/LICENSE
ptan-0.8.1.dist-info/METADATA
ptan-0.8.1.dist-info/WHEEL
ptan-0.8.1.dist-info/top_level.txt
ptan-0.8.1.dist-info/RECORD
